pykailp/__init__.py
pykailp/analyze.py
pykailp/test.py
pykailp/NER/__init__.py
pykailp/NER/helloner.py
pykailp/augment/__init__.py
pykailp/augment/augment.py
pykailp/augment/ciLin.py
pykailp/augment/eda.py
pykailp/augment/transform.py
pykailp/augment/translate.py
pykailp/segment/__init__.py
pykailp/segment/nroute.py
pykailp-0.0.2.dist-info/LICENSE
pykailp-0.0.2.dist-info/METADATA
pykailp-0.0.2.dist-info/WHEEL
pykailp-0.0.2.dist-info/top_level.txt
pykailp-0.0.2.dist-info/RECORD
