Metadata-Version: 2.1
Name: pykailp
Version: 0.0.2
Summary: Python wrapper for kailp: natural language processing
Home-page: https://github.com/pypa/sampleproject
Author: jiazhikai
Author-email: 15716539228@163.com
License: UNKNOWN
Platform: UNKNOWN
Classifier: Programming Language :: Python :: 3
Classifier: License :: OSI Approved :: MIT License
Classifier: Operating System :: OS Independent
